{
    "id": "i106216",
    "type": "noun",
    "batch": "common",
    "en_word": "negro vine",
    "en_definition": "twining vine with hairy foliage and dark purplish-brown flowers",
    "tr_word": "karazambak",
    "tr_definition": "tüylü yapraklara ve koyu morumsu kahverengi çiçeklere sahip sarılıcı bir asma türü",
    "ru_word": "цинанхум",
    "ru_definition": "вьющаяся лиана с опушенной листвой и темно-пурпурно-коричневыми цветками",
    "clusters": [
        {
            "ortatil": "",
            "cluster": {
                "Turkish": [
                    "kara asma"
                ],
                "Azerbaijani": [
                    "qara sarmaşıq",
                    "qaraçiçək sarmaşıq"
                ],
                "Turkmen": [
                    "gara çyrmaşyk",
                    "gara sarmalyk"
                ],
                "Uyghur": [
                    "قارا پېلەك",
                    "قارا گۈللۈك پېلەك",
                    "قارا پېلەك ئۆسۈملۈكى"
                ],
                "Kazakh": [
                    "қара шырмауық"
                ],
                "Karakalpak": [
                    "qara shırmauıq"
                ],
                "Tatar": [
                    "кара үрмәле гөл",
                    "кара чәчәкле үрмәле гөл"
                ],
                "Bashkir": [
                    "ҡара үрмәле гөл",
                    "ҡара сырмауыҡ"
                ]
            }
        },
        {
            "ortatil": "",
            "cluster": {
                "Turkish": [
                    "tüylü sarmaşık"
                ],
                "Azerbaijani": [
                    "tüklü sarmaşıq"
                ],
                "Kazakh": [
                    "түкті шырмауық"
                ]
            }
        },
        {
            "cluster": {
                "Uzbek": [
                    "chirmashuvchi o'simlik"
                ],
                "Kyrgyz": [
                    "чырмалгыч өсүмдүк",
                    "чырмалгыч гүл",
                    "чырмалгыч"
                ]
            }
        },
        {
            "cluster": {
                "Turkish": [
                    "yabani sarmaşık"
                ]
            }
        },
        {
            "cluster": {
                "Uzbek": [
                    "pechak",
                    "pechakgul"
                ]
            }
        },
        {
            "cluster": {
                "Karakalpak": [
                    "shırmauıq"
                ]
            }
        }
    ]
}
