{
    "id": "i114169",
    "type": "noun",
    "batch": "common",
    "en_word": "opal",
    "en_definition": "a translucent mineral consisting of hydrated silica of variable color; some varieties are used as gemstones",
    "tr_word": "opal",
    "tr_definition": "Değişken renkli, hidratlı silisli, yarı saydam bir mineral; bazı çeşitleri değerli taş olarak kullanılır.",
    "ru_word": "опал",
    "ru_definition": "Полупрозрачный минерал, состоящий из гидратированного кремнезема переменного цвета; некоторые разновидности используются в качестве драгоценных камней.",
    "clusters": [
        {
            "ortatil": "",
            "cluster": {
                "Turkish": [
                    "opal"
                ],
                "Azerbaijani": [
                    "opal"
                ],
                "Turkmen": [
                    "opal"
                ],
                "Uzbek": [
                    "opal"
                ],
                "Uyghur": [
                    "ئوپال"
                ],
                "Kazakh": [
                    "опал"
                ],
                "Kyrgyz": [
                    "опал"
                ],
                "Karakalpak": [
                    "opal"
                ],
                "Tatar": [
                    "опал"
                ],
                "Bashkir": [
                    "опал"
                ]
            }
        },
        {
            "ortatil": "",
            "cluster": {
                "Uyghur": [
                    "ئاق تاش"
                ],
                "Kazakh": [
                    "асыл тас"
                ],
                "Kyrgyz": [
                    "асыл таш"
                ],
                "Karakalpak": [
                    "asıl tas"
                ]
            }
        },
        {
            "ortatil": "",
            "cluster": {
                "Uzbek": [
                    "koʻzmunchoq"
                ],
                "Kyrgyz": [
                    "көз мончок"
                ],
                "Tatar": [
                    "күзташ"
                ]
            }
        },
        {
            "cluster": {
                "Turkish": [
                    "panzehir taşı"
                ]
            }
        },
        {
            "cluster": {
                "Turkish": [
                    "gökkuşağı taşı"
                ]
            }
        },
        {
            "cluster": {
                "Azerbaijani": [
                    "eynişəms"
                ]
            }
        },
        {
            "cluster": {
                "Azerbaijani": [
                    "pəpəz"
                ]
            }
        },
        {
            "cluster": {
                "Turkmen": [
                    "älemgoşar daşy"
                ]
            }
        },
        {
            "cluster": {
                "Uzbek": [
                    "marvaridshakl"
                ]
            }
        },
        {
            "cluster": {
                "Uyghur": [
                    "سۈت تاش"
                ]
            }
        },
        {
            "cluster": {
                "Kazakh": [
                    "құбылмалы тас"
                ]
            }
        },
        {
            "cluster": {
                "Bashkir": [
                    "аҡыҡ"
                ]
            }
        }
    ]
}
