{
    "id": "isaretlemek--tick-off",
    "type": "",
    "batch": "karshilashtirmali",
    "en_word": "tick off",
    "en_definition": "tick off",
    "tr_word": "işaretlemek",
    "tr_definition": "işaretlemek",
    "ru_word": "пометить",
    "ru_definition": "пометить, обозначить",
    "synonyms": {
        "tur": [
            "işaretlemek"
        ],
        "aze": [
            "işãrätlämäk"
        ],
        "tuk": [
            "belgilemek"
        ],
        "uzb": [
            "belgilamoq",
            "belgi qoʻymoq"
        ],
        "uig": [
            "bälgülimäk"
        ],
        "kaz": [
            "belgilev",
            "taŋbalav"
        ],
        "kir": [
            "belgi koyū",
            "tamğa salū"
        ],
        "kaa": [],
        "tat": [
            "bilgi (tamğa) salu",
            "tamğalav"
        ],
        "bak": [
            "bildä kuyıv",
            "tamğa kuyıv",
            "huğıv"
        ]
    }
}