{
    "id": "i16440",
    "type": "adjective",
    "batch": "common",
    "en_word": "maritime",
    "en_definition": "relating to or involving ships or shipping or navigation or seamen",
    "tr_word": "denizcilikle ilgili",
    "tr_definition": "gemiler, deniz taşımacılığı veya denizcilikle ilgili olan",
    "ru_word": "морской",
    "ru_definition": "связанный с морем, судоходством или деятельностью моряков",
    "clusters": [
        {
            "ortatil": "",
            "cluster": {
                "Turkish": [
                    "deniz",
                    "denizcilik"
                ],
                "Azerbaijani": [
                    "dəniz",
                    "dənizçilik"
                ],
                "Turkmen": [
                    "deňiz",
                    "deňizçilik"
                ],
                "Uzbek": [
                    "dengizga oid",
                    "dengizchilik"
                ],
                "Uyghur": [
                    "دېڭىزچىلىق",
                    "دېڭىزغا ئائىت",
                    "دېڭىز سەپىرىگە ئائىت"
                ],
                "Kazakh": [
                    "теңіздік",
                    "теңіз"
                ],
                "Kyrgyz": [
                    "деңиздик",
                    "деңиз"
                ],
                "Karakalpak": [
                    "teńiz",
                    "teńizshilik"
                ],
                "Tatar": [
                    "диңгез",
                    "диңгезчелек"
                ],
                "Bashkir": [
                    "диңгеҙ",
                    "диңгеҙселек"
                ]
            }
        },
        {
            "ortatil": "",
            "cluster": {
                "Turkmen": [
                    "gämiçilik"
                ],
                "Uzbek": [
                    "kemachilik"
                ],
                "Uyghur": [
                    "كېمىچىلىك"
                ],
                "Kazakh": [
                    "кемешілік",
                    "кеме қатынасы"
                ],
                "Kyrgyz": [
                    "кемечилик"
                ],
                "Karakalpak": [
                    "kemeshilik"
                ],
                "Tatar": [
                    "көймәчелек"
                ],
                "Bashkir": [
                    "кәмәселек"
                ]
            }
        },
        {
            "ortatil": "",
            "cluster": {
                "Turkish": [
                    "bahri"
                ],
                "Azerbaijani": [
                    "bəhri"
                ],
                "Uzbek": [
                    "bahriy"
                ]
            }
        },
        {
            "cluster": {
                "Turkish": [
                    "sefine"
                ]
            }
        }
    ]
}
