{
    "id": "i87053",
    "type": "noun",
    "batch": "common",
    "en_word": "abel",
    "en_definition": "(Old Testament) Cain and Abel were the first children of Adam and Eve born after the Fall of Man; Abel was killed by Cain",
    "tr_word": "Habil",
    "tr_definition": "Adem ve Havva'nın ikinci oğlu, kardeşi Kabil tarafından öldürülen peygamber veya dini figür.",
    "ru_word": "Авель",
    "ru_definition": "Второй сын Адама и Евы, убитый своим братом Каином.",
    "clusters": [
        {
            "ortatil": "",
            "cluster": {
                "Turkish": [
                    "Habil"
                ],
                "Azerbaijani": [
                    "Habil"
                ],
                "Turkmen": [
                    "Habyl"
                ],
                "Uzbek": [
                    "Hobil"
                ],
                "Uyghur": [
                    "ھابىل",
                    "ھابىل ئەلەيھىسسالام"
                ],
                "Kazakh": [
                    "Әбіл"
                ],
                "Kyrgyz": [
                    "Абыл"
                ],
                "Karakalpak": [
                    "Hábil",
                    "Abıl"
                ],
                "Tatar": [
                    "Һабил"
                ],
                "Bashkir": [
                    "Һабил"
                ]
            }
        },
        {
            "cluster": {
                "Kazakh": [
                    "Әбіл пайғамбар"
                ],
                "Bashkir": [
                    "Һабил пәйғәмбәр"
                ]
            }
        }
    ]
}
