{
    "id": "i37472",
    "type": "noun",
    "batch": "common",
    "en_word": "extraction",
    "en_definition": "the action of taking out something (especially using effort or force)",
    "tr_word": "çıkarma",
    "tr_definition": "Bir şeyi bulunduğu yerden çekip alma veya dışarı çıkarma eylemi.",
    "ru_word": "извлечение",
    "ru_definition": "Процесс вынимания или удаления чего-либо откуда-либо с применением усилий.",
    "clusters": [
        {
            "ortatil": "",
            "cluster": {
                "Turkish": [
                    "çıkarma",
                    "çekme",
                    "sökme"
                ],
                "Azerbaijani": [
                    "çıxarma",
                    "çıxarılma",
                    "çəkmə"
                ],
                "Turkmen": [
                    "çykaryş",
                    "çykarmaklyk"
                ],
                "Uzbek": [
                    "chiqarish"
                ],
                "Uyghur": [
                    "چىقىرىش"
                ],
                "Kazakh": [
                    "шығару"
                ],
                "Kyrgyz": [
                    "чыгаруу"
                ],
                "Karakalpak": [
                    "shıǵarıu"
                ],
                "Tatar": [
                    "чыгару"
                ],
                "Bashkir": [
                    "сығарыу"
                ]
            }
        },
        {
            "ortatil": "",
            "cluster": {
                "Uzbek": [
                    "sug'urish"
                ],
                "Uyghur": [
                    "سۇغۇرۇش"
                ],
                "Kyrgyz": [
                    "сууруу"
                ],
                "Karakalpak": [
                    "suırıu"
                ],
                "Tatar": [
                    "суырып алу"
                ]
            }
        },
        {
            "ortatil": "",
            "cluster": {
                "Uyghur": [
                    "تارتىپ چىقىرىش"
                ],
                "Kazakh": [
                    "тартып алу"
                ],
                "Karakalpak": [
                    "tartıp alıu"
                ],
                "Tatar": [
                    "тартып алу"
                ],
                "Bashkir": [
                    "тартып алыу"
                ]
            }
        },
        {
            "ortatil": "",
            "cluster": {
                "Turkish": [
                    "istihraç"
                ],
                "Azerbaijani": [
                    "istixrac"
                ],
                "Turkmen": [
                    "istihraj"
                ]
            }
        },
        {
            "ortatil": "",
            "cluster": {
                "Uzbek": [
                    "ajratish"
                ],
                "Uyghur": [
                    "ئاجرىتىپ ئېلىش"
                ],
                "Karakalpak": [
                    "ajıratıu"
                ]
            }
        },
        {
            "cluster": {
                "Turkmen": [
                    "gazyp alyş"
                ],
                "Kyrgyz": [
                    "казып алуу"
                ]
            }
        },
        {
            "cluster": {
                "Uzbek": [
                    "olish"
                ],
                "Tatar": [
                    "алу"
                ]
            }
        },
        {
            "cluster": {
                "Kazakh": [
                    "айыру"
                ],
                "Bashkir": [
                    "айырып алыу",
                    "айырыу"
                ]
            }
        },
        {
            "cluster": {
                "Kazakh": [
                    "бөліп алу"
                ],
                "Kyrgyz": [
                    "бөлүп алуу"
                ]
            }
        }
    ]
}
