{
    "id": "gormek--see",
    "type": "",
    "batch": "karshilashtirmali",
    "en_word": "see",
    "en_definition": "see, witness",
    "tr_word": "görmek",
    "tr_definition": "görmek",
    "ru_word": "видеть",
    "ru_definition": "видеть",
    "synonyms": {
        "tur": [
            "görmek"
        ],
        "aze": [
            "görmäk"
        ],
        "tuk": [
            "görmek"
        ],
        "uzb": [
            "koʻrmoq"
        ],
        "uig": [
            "körmäk"
        ],
        "kaz": [
            "körüv"
        ],
        "kir": [
            "körṻ",
            "tiktȫ"
        ],
        "kaa": [],
        "tat": [
            "kürü"
        ],
        "bak": [
            "küriv"
        ]
    }
}