{
    "id": "cala-kalem-yazmak--scribble",
    "type": "",
    "batch": "karshilashtirmali",
    "en_word": "scribble",
    "en_definition": "scribble",
    "tr_word": "çala kalem (yazmak)",
    "tr_definition": "çala kalem (yazmak)",
    "ru_word": "строчить",
    "ru_definition": "строчить",
    "synonyms": {
        "tur": [
            "çala kalem (yazmak)"
        ],
        "aze": [
            "e'tinãsız",
            "täläsik (yazmak)"
        ],
        "tuk": [
            "çalasovat",
            "çiğ-çarsı"
        ],
        "uzb": [
            "chala-chulpa (yozmoq)"
        ],
        "uig": [
            "çala-puçuk (yazmak)"
        ],
        "kaz": [
            "şala-pula",
            "üstirtin"
        ],
        "kir": [
            "çala sabat",
            "çabal"
        ],
        "kaa": [],
        "tat": [
            "aşığıçlık bilän",
            "kabalanıp (yazu)"
        ],
        "bak": [
            "sıymaklav",
            "aşığıs",
            "kabalanlık bilän (yaⱬıv)"
        ]
    }
}