{
    "id": "i66132",
    "type": "noun",
    "batch": "common",
    "en_word": "buttocks",
    "en_definition": "the fleshy part of the human body that you sit on",
    "tr_word": "kıç",
    "tr_definition": "insan vücudunun üzerine oturulan etli kısmı",
    "ru_word": "задница",
    "ru_definition": "мясистая часть человеческого тела, на которой сидят",
    "clusters": [
        {
            "ortatil": "",
            "cluster": {
                "Turkish": [
                    "sağrı"
                ],
                "Azerbaijani": [
                    "sağrı"
                ],
                "Turkmen": [
                    "saňry",
                    "saňra"
                ],
                "Uyghur": [
                    "ساغرا"
                ],
                "Karakalpak": [
                    "sauır"
                ],
                "Tatar": [
                    "савыт"
                ]
            }
        },
        {
            "ortatil": "",
            "cluster": {
                "Azerbaijani": [
                    "arxa"
                ],
                "Uzbek": [
                    "arqa"
                ],
                "Kazakh": [
                    "арқа"
                ],
                "Kyrgyz": [
                    "арка"
                ],
                "Karakalpak": [
                    "arqa"
                ],
                "Bashkir": [
                    "арт",
                    "арт һаны"
                ]
            }
        },
        {
            "ortatil": "",
            "cluster": {
                "Turkmen": [
                    "gotaz"
                ],
                "Kazakh": [
                    "көтен"
                ],
                "Kyrgyz": [
                    "көт"
                ],
                "Tatar": [
                    "күт"
                ]
            }
        },
        {
            "ortatil": "",
            "cluster": {
                "Uzbek": [
                    "quymich"
                ],
                "Kyrgyz": [
                    "куйрук"
                ],
                "Bashkir": [
                    "көйөш"
                ]
            }
        },
        {
            "ortatil": "",
            "cluster": {
                "Kazakh": [
                    "бөксе"
                ],
                "Karakalpak": [
                    "bókse"
                ],
                "Tatar": [
                    "бөксә"
                ]
            }
        },
        {
            "ortatil": "",
            "cluster": {
                "Kazakh": [
                    "жамбас"
                ],
                "Kyrgyz": [
                    "жамбаш"
                ],
                "Karakalpak": [
                    "jambas"
                ]
            }
        },
        {
            "cluster": {
                "Turkish": [
                    "kalça",
                    "kıç"
                ],
                "Uyghur": [
                    "كاسا"
                ]
            }
        },
        {
            "cluster": {
                "Turkish": [
                    "but"
                ],
                "Azerbaijani": [
                    "bud"
                ]
            }
        },
        {
            "cluster": {
                "Azerbaijani": [
                    "yan"
                ],
                "Turkmen": [
                    "ýanbaş"
                ]
            }
        },
        {
            "cluster": {
                "Turkmen": [
                    "omça"
                ]
            }
        },
        {
            "cluster": {
                "Uzbek": [
                    "dumb"
                ]
            }
        },
        {
            "cluster": {
                "Uzbek": [
                    "ket"
                ]
            }
        },
        {
            "cluster": {
                "Uyghur": [
                    "تەرەتگاھ"
                ]
            }
        },
        {
            "cluster": {
                "Uyghur": [
                    "داس"
                ]
            }
        },
        {
            "cluster": {
                "Bashkir": [
                    "ултырғыс"
                ]
            }
        }
    ]
}
