{
    "id": "i11816",
    "type": "adjective",
    "batch": "common",
    "en_word": "shared",
    "en_definition": "have in common; held or experienced in common",
    "tr_word": "ortak",
    "tr_definition": "Birden fazla kişi veya grup tarafından paylaşılan, müşterek olan.",
    "ru_word": "общий",
    "ru_definition": "Принадлежащий или свойственный всем, многим или обоим.",
    "clusters": [
        {
            "ortatil": "",
            "cluster": {
                "Turkish": [
                    "ortak"
                ],
                "Azerbaijani": [
                    "ortaq"
                ],
                "Turkmen": [
                    "ortak"
                ],
                "Uyghur": [
                    "ئورتاق"
                ],
                "Kazakh": [
                    "ортақ"
                ],
                "Kyrgyz": [
                    "орток"
                ],
                "Karakalpak": [
                    "ortaq"
                ],
                "Tatar": [
                    "уртак"
                ],
                "Bashkir": [
                    "уртаҡ"
                ]
            }
        },
        {
            "ortatil": "",
            "cluster": {
                "Turkish": [
                    "müşterek"
                ],
                "Azerbaijani": [
                    "müştərək"
                ],
                "Turkmen": [
                    "müşterek"
                ],
                "Uzbek": [
                    "mushtarak"
                ],
                "Uyghur": [
                    "مۇشتەرەك"
                ]
            }
        },
        {
            "ortatil": "",
            "cluster": {
                "Kazakh": [
                    "бірлескен",
                    "бөлісілген"
                ],
                "Kyrgyz": [
                    "биргелешкен"
                ],
                "Karakalpak": [
                    "birgelesken"
                ],
                "Tatar": [
                    "бергәләп",
                    "бердәм"
                ],
                "Bashkir": [
                    "берҙәм"
                ]
            }
        },
        {
            "ortatil": "",
            "cluster": {
                "Azerbaijani": [
                    "ümumi"
                ],
                "Turkmen": [
                    "umumy"
                ],
                "Uzbek": [
                    "umumiy"
                ]
            }
        },
        {
            "cluster": {
                "Turkish": [
                    "paylaşılan"
                ]
            }
        },
        {
            "cluster": {
                "Uzbek": [
                    "sheriklik"
                ]
            }
        },
        {
            "cluster": {
                "Uzbek": [
                    "hamkorlikdagi"
                ]
            }
        },
        {
            "cluster": {
                "Uyghur": [
                    "ھەمبەھىر"
                ]
            }
        },
        {
            "cluster": {
                "Kazakh": [
                    "қауымдық"
                ]
            }
        },
        {
            "cluster": {
                "Kyrgyz": [
                    "жалпы"
                ]
            }
        },
        {
            "cluster": {
                "Karakalpak": [
                    "jámáátlik"
                ]
            }
        },
        {
            "cluster": {
                "Bashkir": [
                    "аралаш"
                ]
            }
        }
    ]
}
