{
    "id": "koltuk-oturmak-icin--chair",
    "type": "",
    "batch": "karshilashtirmali",
    "en_word": "chair",
    "en_definition": "chair, armchair",
    "tr_word": "koltuk (oturmak için)",
    "tr_definition": "koltuk (oturmak için)",
    "ru_word": "кресло",
    "ru_definition": "кресло",
    "synonyms": {
        "tur": [
            "koltuk (oturmak için)"
        ],
        "aze": [
            "kreslo",
            "goltuglu kürsü"
        ],
        "tuk": [
            "kreslo"
        ],
        "uzb": [
            "kreslo"
        ],
        "uig": [
            "kursi"
        ],
        "kaz": [
            "kalkandı şıntaktı orındık",
            "kreslo"
        ],
        "kir": [
            "orunduk",
            "kreslo"
        ],
        "kaa": [],
        "tat": [
            "kreslo"
        ],
        "bak": [
            "kreslo"
        ]
    }
}