{
    "id": "i4260",
    "type": "adjective",
    "batch": "common",
    "en_word": "bigmouthed",
    "en_definition": "unwisely talking too much",
    "tr_word": "boşboğaz",
    "tr_definition": "sır saklayamayan, her şeyi her yerde söyleyen, konuşkanlığıyla başkalarını rahatsız eden",
    "ru_word": "болтливый",
    "ru_definition": "склонный много говорить, не умеющий хранить секреты или говорящий лишнее",
    "clusters": [
        {
            "ortatil": "",
            "cluster": {
                "Azerbaijani": [
                    "laqqı"
                ],
                "Turkmen": [
                    "lakgy"
                ],
                "Kazakh": [
                    "лақпа"
                ],
                "Kyrgyz": [
                    "лакылдак"
                ],
                "Karakalpak": [
                    "laqqı"
                ]
            }
        },
        {
            "ortatil": "",
            "cluster": {
                "Turkmen": [
                    "agzyboş"
                ],
                "Uzbek": [
                    "og'zi bo'sh"
                ],
                "Uyghur": [
                    "ئاغزى بوش"
                ],
                "Karakalpak": [
                    "aozı bos"
                ]
            }
        },
        {
            "ortatil": "",
            "cluster": {
                "Kazakh": [
                    "көпсөзді"
                ],
                "Kyrgyz": [
                    "көп сүйлөөк"
                ],
                "Karakalpak": [
                    "kópsóylegish"
                ],
                "Bashkir": [
                    "күп һөйләүсе"
                ]
            }
        },
        {
            "ortatil": "",
            "cluster": {
                "Turkish": [
                    "lafazan"
                ],
                "Uzbek": [
                    "lapashang"
                ],
                "Uyghur": [
                    "لاپچى"
                ]
            }
        },
        {
            "ortatil": "",
            "cluster": {
                "Azerbaijani": [
                    "çərənçi"
                ],
                "Uzbek": [
                    "sergap"
                ],
                "Tatar": [
                    "серсез"
                ]
            }
        },
        {
            "ortatil": "",
            "cluster": {
                "Azerbaijani": [
                    "dillidilavər"
                ],
                "Tatar": [
                    "телчән",
                    "тел бистәсе"
                ],
                "Bashkir": [
                    "тел биҫтәһе",
                    "телсәр",
                    "телмәр",
                    "тел биреүсе"
                ]
            }
        },
        {
            "ortatil": "",
            "cluster": {
                "Uzbek": [
                    "ezma"
                ],
                "Kazakh": [
                    "езбе"
                ],
                "Karakalpak": [
                    "ezi"
                ]
            }
        },
        {
            "cluster": {
                "Turkish": [
                    "boşboğaz"
                ],
                "Azerbaijani": [
                    "boşboğaz"
                ]
            }
        },
        {
            "cluster": {
                "Kazakh": [
                    "аузы-мұрнына ие болмайтын"
                ],
                "Tatar": [
                    "авыз йоммый торган"
                ]
            }
        },
        {
            "cluster": {
                "Turkish": [
                    "geveze"
                ]
            }
        },
        {
            "cluster": {
                "Turkish": [
                    "patavatsız"
                ]
            }
        },
        {
            "cluster": {
                "Azerbaijani": [
                    "boğazıboş"
                ]
            }
        },
        {
            "cluster": {
                "Turkmen": [
                    "gepçil",
                    "gepçi"
                ]
            }
        },
        {
            "cluster": {
                "Uzbek": [
                    "vaysaqi"
                ]
            }
        },
        {
            "cluster": {
                "Uyghur": [
                    "ھەرزەگو"
                ]
            }
        },
        {
            "cluster": {
                "Uyghur": [
                    "پاشپاش"
                ]
            }
        },
        {
            "cluster": {
                "Kazakh": [
                    "мылжың"
                ]
            }
        },
        {
            "cluster": {
                "Kyrgyz": [
                    "ооз көптүрмө",
                    "оозу бош"
                ]
            }
        },
        {
            "cluster": {
                "Kyrgyz": [
                    "шакылдак"
                ]
            }
        },
        {
            "cluster": {
                "Tatar": [
                    "сер саклый белмәгән"
                ]
            }
        }
    ]
}
